pyshmht3/Cacher.py
pyshmht3/HashTable.py
pyshmht3/__init__.py
pyshmht3/raw_performance_test.py
pyshmht3-0.1.1.dist-info/LICENSE
pyshmht3-0.1.1.dist-info/WHEEL
pyshmht3-0.1.1.dist-info/METADATA
pyshmht3-0.1.1.dist-info/RECORD
